odoo10_addon_stock_change_qty_reason-10.0.1.0.1-py3.8-nspkg.pth
odoo/addons/stock_change_qty_reason/README.rst
odoo/addons/stock_change_qty_reason/__init__.py
odoo/addons/stock_change_qty_reason/__manifest__.py
odoo/addons/stock_change_qty_reason/i18n/ar.po
odoo/addons/stock_change_qty_reason/i18n/bs.po
odoo/addons/stock_change_qty_reason/i18n/ca.po
odoo/addons/stock_change_qty_reason/i18n/cs.po
odoo/addons/stock_change_qty_reason/i18n/cs_CZ.po
odoo/addons/stock_change_qty_reason/i18n/de.po
odoo/addons/stock_change_qty_reason/i18n/en_GB.po
odoo/addons/stock_change_qty_reason/i18n/es.po
odoo/addons/stock_change_qty_reason/i18n/es_CR.po
odoo/addons/stock_change_qty_reason/i18n/es_EC.po
odoo/addons/stock_change_qty_reason/i18n/es_MX.po
odoo/addons/stock_change_qty_reason/i18n/es_VE.po
odoo/addons/stock_change_qty_reason/i18n/et.po
odoo/addons/stock_change_qty_reason/i18n/fi.po
odoo/addons/stock_change_qty_reason/i18n/fr.po
odoo/addons/stock_change_qty_reason/i18n/hr.po
odoo/addons/stock_change_qty_reason/i18n/hu.po
odoo/addons/stock_change_qty_reason/i18n/it.po
odoo/addons/stock_change_qty_reason/i18n/ja.po
odoo/addons/stock_change_qty_reason/i18n/lt.po
odoo/addons/stock_change_qty_reason/i18n/mk.po
odoo/addons/stock_change_qty_reason/i18n/mn.po
odoo/addons/stock_change_qty_reason/i18n/nb.po
odoo/addons/stock_change_qty_reason/i18n/nl.po
odoo/addons/stock_change_qty_reason/i18n/nl_BE.po
odoo/addons/stock_change_qty_reason/i18n/nl_NL.po
odoo/addons/stock_change_qty_reason/i18n/pl.po
odoo/addons/stock_change_qty_reason/i18n/pt.po
odoo/addons/stock_change_qty_reason/i18n/pt_BR.po
odoo/addons/stock_change_qty_reason/i18n/pt_PT.po
odoo/addons/stock_change_qty_reason/i18n/ro.po
odoo/addons/stock_change_qty_reason/i18n/ru.po
odoo/addons/stock_change_qty_reason/i18n/sl.po
odoo/addons/stock_change_qty_reason/i18n/sr@latin.po
odoo/addons/stock_change_qty_reason/i18n/stock_change_qty_reason.pot
odoo/addons/stock_change_qty_reason/i18n/sv.po
odoo10_addon_stock_change_qty_reason-10.0.1.0.1.dist-info/METADATA
odoo10_addon_stock_change_qty_reason-10.0.1.0.1.dist-info/WHEEL
odoo10_addon_stock_change_qty_reason-10.0.1.0.1.dist-info/namespace_packages.txt
odoo10_addon_stock_change_qty_reason-10.0.1.0.1.dist-info/top_level.txt
odoo10_addon_stock_change_qty_reason-10.0.1.0.1.dist-info/RECORD
